[{"model": "legal_advice_builder.lawcase", "pk": 1, "fields": {"title": "Sample Law Case", "description": "Lorem ipsum dolor sit amet, consetetur sadipscing elitr, sed diam nonumy eirmod tempor invidunt ut labore et dolore magna aliquyam erat, sed diam voluptua. At vero eos et accusam et justo duo dolores et ea rebum. Stet clita kasd gubergren, no sea takimata sanctus est Lorem ipsum dolor sit amet. Lorem ipsum dolor sit amet, consetetur sadipscing elitr, sed diam nonumy eirmod tempor invidunt ut labore et dolore magna aliquyam erat, sed diam voluptua. At vero eos et accusam et justo duo dolores et ea rebum. Stet clita kasd gubergren, no sea takimata sanctus est Lorem ipsum dolor sit amet.", "result_template": "<p>This is your name an address!</p>\r\n\r\n<p>\r\n<b>{{ answers.questionaire_2_name }}</b></br>\r\n{{ answers.questionaire_2_address }}\r\n</p>"}}, {"model": "legal_advice_builder.questionaire", "pk": 1, "fields": {"law_case": 1, "title": "Sample Questionaire 1", "short_title": "questionaire_1", "success_message": "This is a success message", "failure_message": "This is a failure message", "unsure_message": "This is an unsure message", "order": 1}}, {"model": "legal_advice_builder.questionaire", "pk": 2, "fields": {"law_case": 1, "title": "Sample Questionaire 2", "short_title": "questionaire_2", "success_message": "Success!", "failure_message": "Failure!", "unsure_message": "Unsure!", "order": 2}}, {"model": "legal_advice_builder.question", "pk": 1, "fields": {"path": "0001", "depth": 1, "numchild": 1, "questionaire": 1, "short_title": "sample_1", "text": "Are you 18 years or older?", "options": {"yes": "yes", "no": "no"}, "field_type": "SO", "help_text": "", "parent_option": "", "failure_options": ["no"], "success_options": [], "unsure_options": [], "information": "", "success_message": "", "failure_message": "", "unsure_message": ""}}, {"model": "legal_advice_builder.question", "pk": 2, "fields": {"path": "00010001", "depth": 2, "numchild": 1, "questionaire": 1, "short_title": "sample_2", "text": "Did you hand in that form more then 3 month ago?", "options": {"yes": "yes, I did", "no": "no"}, "field_type": "SO", "help_text": "", "parent_option": "yes", "failure_options": ["no"], "success_options": [], "unsure_options": [], "information": "", "success_message": "", "failure_message": "", "unsure_message": ""}}, {"model": "legal_advice_builder.question", "pk": 3, "fields": {"path": "000100010001", "depth": 3, "numchild": 2, "questionaire": 1, "short_title": "sample_3", "text": "What happened next?", "options": {"nothing": "nothing", "letter": "I received an letter", "call": "someone called me"}, "field_type": "SO", "help_text": "", "parent_option": "yes", "failure_options": [], "success_options": ["nothing"], "unsure_options": [], "information": "", "success_message": "", "failure_message": "", "unsure_message": ""}}, {"model": "legal_advice_builder.question", "pk": 4, "fields": {"path": "0001000100010001", "depth": 4, "numchild": 0, "questionaire": 1, "short_title": "", "text": "What was written in that letter?", "options": {"nothing": "nothing", "something": "something"}, "field_type": "SO", "help_text": "", "parent_option": "letter", "failure_options": ["something"], "success_options": ["nothing"], "unsure_options": [], "information": "", "success_message": "", "failure_message": "", "unsure_message": ""}}, {"model": "legal_advice_builder.question", "pk": 5, "fields": {"path": "0001000100010002", "depth": 4, "numchild": 0, "questionaire": 1, "short_title": "", "text": "What did this person say?", "options": {"nothing": "nothing", "something": "something"}, "field_type": "SO", "help_text": "", "parent_option": "call", "failure_options": ["something"], "success_options": ["nothing"], "unsure_options": [], "information": "", "success_message": "", "failure_message": "", "unsure_message": ""}}, {"model": "legal_advice_builder.question", "pk": 6, "fields": {"path": "0002", "depth": 1, "numchild": 1, "questionaire": 2, "short_title": "name", "text": "What is your name?", "options": {}, "field_type": "SL", "help_text": "", "parent_option": "", "failure_options": [], "success_options": [], "unsure_options": [], "information": "", "success_message": "", "failure_message": "", "unsure_message": ""}}, {"model": "legal_advice_builder.question", "pk": 7, "fields": {"path": "00020001", "depth": 2, "numchild": 0, "questionaire": 2, "short_title": "address", "text": "What is your address", "options": {}, "field_type": "TX", "help_text": "", "parent_option": "", "failure_options": [], "success_options": [], "unsure_options": [], "information": "", "success_message": "", "failure_message": "", "unsure_message": ""}}]